pdflib-0.3.0.dist-info/RECORD
pdflib-0.3.0.dist-info/WHEEL
pdflib-0.3.0.dist-info/top_level.txt
pdflib-0.3.0.dist-info/METADATA
pdflib/utils.py
pdflib/poppler.cpython-35m-x86_64-linux-gnu.so
pdflib/__init__.py
pdflib.libs/libz-eb09ad1d.so.1.2.3
pdflib.libs/libexpat-64fa60ba.so.1.5.2
pdflib.libs/libpng12-640ca796.so.0.49.0
pdflib.libs/libpoppler-530843d8.so.74.0.0
pdflib.libs/libpoppler-cpp-d7b793a8.so.0.4.0
pdflib.libs/libfontconfig-63352676.so.1.4.4
pdflib.libs/libtiff-e6ae6939.so.3.9.4
pdflib.libs/libjpeg-7feae879.so.62.0.0
pdflib.libs/libfreetype-20bfc0cd.so.6.3.22
