Metadata-Version: 2.1
Name: pdflib
Version: 0.3.0
Summary: python bindings for poppler
Home-page: http://github.com/alephdata/pdflib
Author: Journalism Development Network
Author-email: data@occrp.org
License: GPLv3
Platform: UNKNOWN
Requires-Dist: cython
Requires-Dist: lxml
Requires-Dist: six
